README.rst
setup.cfg
setup.py
scpy/__init__.py
scpy/consensus.py
scpy/daemon.py
scpy/gateway.py
scpy/host.py
scpy/hostdb.py
scpy/renter.py
scpy/sia_client.py
scpy/tpool.py
scpy/wallet.py
sia_scpy.egg-info/PKG-INFO
sia_scpy.egg-info/SOURCES.txt
sia_scpy.egg-info/dependency_links.txt
sia_scpy.egg-info/requires.txt
sia_scpy.egg-info/top_level.txt